r00textutil/__init__.py
r00textutil/find_in_files.py
r00textutil/replace.py
r00textutil-0.1.4.dist-info/METADATA
r00textutil-0.1.4.dist-info/WHEEL
r00textutil-0.1.4.dist-info/RECORD
