Metadata-Version: 2.4
Name: r00textutil
Version: 0.1.4
Requires-Python: >=3.10
Requires-Dist: r00logger
Requires-Dist: r00system
Requires-Dist: rich
Requires-Dist: tqdm
